mindsett_energy_reports_pkg/__init__.py
mindsett_energy_reports_pkg/config/__init__.py
mindsett_energy_reports_pkg/config/email/__init__.py
mindsett_energy_reports_pkg/config/monday/__init__.py
mindsett_energy_reports_pkg/config/monday/auth/__init__.py
mindsett_energy_reports_pkg/config/monday/columns_concerned/__init__.py
mindsett_energy_reports_pkg/config/postgresdb/__init__.py
mindsett_energy_reports_pkg/config/postgresdb/table/__init__.py
mindsett_energy_reports_pkg/config/postgresdb/table_building/__init__.py
mindsett_energy_reports_pkg/config/postgresdb/table_building_total/__init__.py
mindsett_energy_reports_pkg/config/postgresdb/table_cache/__init__.py
mindsett_energy_reports_pkg/config/postgresdb/table_iot/__init__.py
mindsett_energy_reports_pkg/config/postgresdb/table_mailing/__init__.py
mindsett_energy_reports_pkg/config/postgresdb/table_meta/__init__.py
mindsett_energy_reports_pkg/config/postgresdb/table_occupancy/__init__.py
mindsett_energy_reports_pkg/config/postgresdb/table_on_off/__init__.py
mindsett_energy_reports_pkg/config/postgresdb/table_org/__init__.py
mindsett_energy_reports_pkg/config/postgresdb/table_price/__init__.py
mindsett_energy_reports_pkg/config/postgresdb/table_schedule/__init__.py
mindsett_energy_reports_pkg/config/postgresdb/table_sqm/__init__.py
mindsett_energy_reports_pkg/config/postgresdb/table_timezone/__init__.py
mindsett_energy_reports_pkg/config/sharepoint/__init__.py
mindsett_energy_reports_pkg/config/sharepoint/excel/__init__.py
mindsett_energy_reports_pkg/config/sharepoint/excel/columns_concerned/__init__.py
mindsett_energy_reports_pkg/config/smtp/__init__.py
mindsett_energy_reports_pkg/jobs/databricks_job.py
mindsett_energy_reports_pkg/libs/__init__.py
mindsett_energy_reports_pkg/libs/MondayProcessor/__init__.py
mindsett_energy_reports_pkg/libs/MondayProcessor/_fetchBoardById.py
mindsett_energy_reports_pkg/libs/MondayProcessor/_fetchBoardLogsById.py
energy_reports_pkg-0.7.14.dist-info/METADATA
energy_reports_pkg-0.7.14.dist-info/WHEEL
energy_reports_pkg-0.7.14.dist-info/top_level.txt
energy_reports_pkg-0.7.14.dist-info/RECORD
